datasure/.streamlit/config.toml
datasure/__init__.py
datasure/app.py
datasure/assets/IPA-primary-color-CMYK.jpg
datasure/assets/IPA-primary-full-color-abbreviated.png
datasure/assets/LinkedIn Cover IPA20.png
datasure/assets/SurveyCTO-Logo-CMYK.png
datasure/assets/code.png
datasure/assets/datasure_logo.svg
datasure/assets/hard-disk.png
datasure/assets/microsoft_azure.png
datasure/assets/python.png
datasure/assets/storage.png
datasure/checks/__init__.py
datasure/checks/backchecks.py
datasure/checks/descriptive.py
datasure/checks/duplicates.py
datasure/checks/enumerator.py
datasure/checks/gpschecks.py
datasure/checks/missing.py
datasure/checks/outliers.py
datasure/checks/progress.py
datasure/checks/summary.py
datasure/cli.py
datasure/connectors/__init__.py
datasure/connectors/local.py
datasure/connectors/script.py
datasure/connectors/scto.py
datasure/processing/__init__.py
datasure/processing/corrections.py
datasure/processing/prep.py
datasure/utils/__init__.py
datasure/utils/cache_utils.py
datasure/utils/chart_utils.py
datasure/utils/dataframe_utils.py
datasure/utils/duckdb_utils.py
datasure/utils/metric_utils.py
datasure/utils/navigations.py
datasure/utils/prep_utils.py
datasure/utils/secure_credentials.py
datasure/utils/settings_utils.py
datasure/views/config_view.py
datasure/views/correction_view.py
datasure/views/import_view.py
datasure/views/output_view_1.py
datasure/views/prep_view.py
datasure/views/start_view.py
datasure-0.5.6.dist-info/WHEEL
datasure-0.5.6.dist-info/entry_points.txt
datasure-0.5.6.dist-info/METADATA
datasure-0.5.6.dist-info/RECORD
