Metadata-Version: 2.3
Name: datasure
Version: 0.5.6
Summary: IPA Data Management System Dashboard
Keywords: data-quality,survey-data,streamlit,monitoring,hfc
Author: Innovations for Poverty Action
Author-email: Innovations for Poverty Action <researchsupport@poverty-action.org>
License: MIT License
Classifier: Development Status :: 4 - Beta
Classifier: Intended Audience :: Developers
Classifier: Intended Audience :: Science/Research
Classifier: License :: OSI Approved :: MIT License
Classifier: Programming Language :: Python :: 3
Classifier: Programming Language :: Python :: 3.11
Classifier: Programming Language :: Python :: 3.12
Classifier: Topic :: Scientific/Engineering :: Information Analysis
Requires-Dist: streamlit>=1.49.0
Requires-Dist: pandas>=2.2.2
Requires-Dist: plotly>=6.2.0
Requires-Dist: numpy>=2.2.3
Requires-Dist: openpyxl>=3.1.5
Requires-Dist: seaborn>=0.13.2
Requires-Dist: scikit-learn>=1.5.2
Requires-Dist: geopy>=2.4.1
Requires-Dist: pysurveycto>=0.0.15
Requires-Dist: requests>=2.32.3
Requires-Dist: streamlit-extras>=0.5.5
Requires-Dist: pyarrow>=16.0.0
Requires-Dist: opencv-python>=4.11.0.86
Requires-Dist: matplotlib>=3.10.0
Requires-Dist: polars>=1.30.0
Requires-Dist: duckdb>=1.3.1
Requires-Dist: pillow>=11.3.0
Requires-Dist: pydantic>=2.11.7
Requires-Dist: keyring>=25.6.0
Requires-Dist: polars-readstat>=0.5.1
Requires-Dist: fastexcel>=0.14.0
Requires-Dist: pytest>=8.0.0 ; extra == 'dev'
Requires-Dist: pytest-cov>=4.1.0 ; extra == 'dev'
Requires-Dist: ruff>=0.6.4 ; extra == 'dev'
Requires-Python: >=3.11
Project-URL: Issues, https://github.com/PovertyAction/datasure/issues
Project-URL: Source, https://github.com/PovertyAction/datasure
Provides-Extra: dev
